pricehist/__init__.py
pricehist/beanprice/__init__.py
pricehist/beanprice/alphavantage.py
pricehist/beanprice/bankofcanada.py
pricehist/beanprice/coinbasepro.py
pricehist/beanprice/coindesk.py
pricehist/beanprice/coinmarketcap.py
pricehist/beanprice/ecb.py
pricehist/beanprice/exchangeratehost.py
pricehist/beanprice/yahoo.py
pricehist/cli.py
pricehist/exceptions.py
pricehist/fetch.py
pricehist/format.py
pricehist/isocurrencies.py
pricehist/logger.py
pricehist/outputs/__init__.py
pricehist/outputs/baseoutput.py
pricehist/outputs/beancount.py
pricehist/outputs/csv.py
pricehist/outputs/gnucashsql.py
pricehist/outputs/json.py
pricehist/outputs/ledger.py
pricehist/price.py
pricehist/resources/__init__.py
pricehist/resources/gnucash.sql
pricehist/resources/list-one.xml
pricehist/resources/list-three.xml
pricehist/series.py
pricehist/sources/__init__.py
pricehist/sources/alphavantage.py
pricehist/sources/bankofcanada.py
pricehist/sources/basesource.py
pricehist/sources/coinbasepro.py
pricehist/sources/coindesk.py
pricehist/sources/coinmarketcap.py
pricehist/sources/ecb.py
pricehist/sources/exchangeratehost.py
pricehist/sources/yahoo.py
pricehist-1.4.14.dist-info/LICENSE
pricehist-1.4.14.dist-info/METADATA
pricehist-1.4.14.dist-info/WHEEL
pricehist-1.4.14.dist-info/entry_points.txt
pricehist-1.4.14.dist-info/RECORD
