Metadata-Version: 2.3
Name: pricehist
Version: 1.4.14
Summary: Fetch and format historical price data
License: MIT
Keywords: historical,prices,plaintext,accounting,csv,gnucash,ledger,hledger,beancount
Author: Chris Berkhout
Author-email: chris@chrisberkhout.com
Requires-Python: >=3.8.1,<4.0.0
Classifier: License :: OSI Approved :: MIT License
Classifier: Programming Language :: Python :: 3
Classifier: Programming Language :: Python :: 3.9
Classifier: Programming Language :: Python :: 3.10
Classifier: Programming Language :: Python :: 3.11
Classifier: Programming Language :: Python :: 3.12
Classifier: Programming Language :: Python :: 3.13
Requires-Dist: cssselect (>=1.1.0,<2.0.0)
Requires-Dist: curlify (>=2.2.1,<3.0.0)
Requires-Dist: lxml (>=5.1.0,<6.0.0)
Requires-Dist: requests (>=2.25.1,<3.0.0)
Project-URL: Homepage, https://gitlab.com/chrisberkhout/pricehist
Project-URL: Repository, https://gitlab.com/chrisberkhout/pricehist
